kaiju_mapper/__init__.py
kaiju_mapper/py.typed
kaiju_mapper-0.1.1.dist-info/METADATA
kaiju_mapper-0.1.1.dist-info/WHEEL
kaiju_mapper-0.1.1.dist-info/RECORD
