Metadata-Version: 2.4
Name: kaiju-mapper
Version: 0.1.1
Summary: Mapper with the noise
Author-email: Ethan Rooke <pypi@ethan.roo.ke>
Requires-Python: >=3.10
Requires-Dist: zen-mapper>=0.2.0
